[
    {
        "name": "id",
        "dbType": "integer,true,true",
        "htmlType": null,
        "validations": null,
        "searchable": false,
        "fillable": false,
        "primary": true,
        "inForm": false,
        "inIndex": false,
        "inView": false
    },
    {
        "name": "user_id",
        "dbType": "integer,false",
        "htmlType": null,
        "validations": "required",
        "searchable": true,
        "fillable": true,
        "primary": false,
        "inForm": true,
        "inIndex": true,
        "inView": true
    },
    {
        "name": "balance",
        "dbType": "float,10,4",
        "htmlType": null,
        "validations": "required",
        "searchable": true,
        "fillable": true,
        "primary": false,
        "inForm": true,
        "inIndex": true,
        "inView": true
    },
    {
        "name": "total_credit",
        "dbType": "float,10,4",
        "htmlType": null,
        "validations": "required",
        "searchable": true,
        "fillable": true,
        "primary": false,
        "inForm": true,
        "inIndex": true,
        "inView": true
    },
    {
        "name": "total_debit",
        "dbType": "float,10,4",
        "htmlType": null,
        "validations": "required",
        "searchable": true,
        "fillable": true,
        "primary": false,
        "inForm": true,
        "inIndex": true,
        "inView": true
    },
    {
        "name": "withdraw_method",
        "dbType": "string,191",
        "htmlType": "text",
        "validations": "required",
        "searchable": true,
        "fillable": true,
        "primary": false,
        "inForm": true,
        "inIndex": true,
        "inView": true
    },
    {
        "name": "payment_email",
        "dbType": "string,191:nullable",
        "htmlType": "text",
        "validations": null,
        "searchable": true,
        "fillable": true,
        "primary": false,
        "inForm": true,
        "inIndex": true,
        "inView": true
    },
    {
        "name": "bank_name",
        "dbType": "string,191:nullable",
        "htmlType": "text",
        "validations": null,
        "searchable": true,
        "fillable": true,
        "primary": false,
        "inForm": true,
        "inIndex": true,
        "inView": true
    },
    {
        "name": "bank_branch",
        "dbType": "string,191:nullable",
        "htmlType": "text",
        "validations": null,
        "searchable": true,
        "fillable": true,
        "primary": false,
        "inForm": true,
        "inIndex": true,
        "inView": true
    },
    {
        "name": "bank_account",
        "dbType": "string,191:nullable",
        "htmlType": "text",
        "validations": null,
        "searchable": true,
        "fillable": true,
        "primary": false,
        "inForm": true,
        "inIndex": true,
        "inView": true
    },
    {
        "name": "applied_for_payout",
        "dbType": "integer,false",
        "htmlType": null,
        "validations": "required",
        "searchable": true,
        "fillable": true,
        "primary": false,
        "inForm": true,
        "inIndex": true,
        "inView": true
    },
    {
        "name": "paid",
        "dbType": "integer,false",
        "htmlType": null,
        "validations": "required",
        "searchable": true,
        "fillable": true,
        "primary": false,
        "inForm": true,
        "inIndex": true,
        "inView": true
    },
    {
        "name": "last_date_applied",
        "dbType": "date:nullable",
        "htmlType": "date",
        "validations": null,
        "searchable": true,
        "fillable": true,
        "primary": false,
        "inForm": true,
        "inIndex": true,
        "inView": true
    },
    {
        "name": "last_date_paid",
        "dbType": "date:nullable",
        "htmlType": "date",
        "validations": null,
        "searchable": true,
        "fillable": true,
        "primary": false,
        "inForm": true,
        "inIndex": true,
        "inView": true
    },
    {
        "name": "country",
        "dbType": "string,191:nullable",
        "htmlType": "text",
        "validations": null,
        "searchable": true,
        "fillable": true,
        "primary": false,
        "inForm": true,
        "inIndex": true,
        "inView": true
    },
    {
        "name": "other_details",
        "dbType": "text:nullable",
        "htmlType": "textarea",
        "validations": null,
        "searchable": true,
        "fillable": true,
        "primary": false,
        "inForm": true,
        "inIndex": true,
        "inView": true
    },
    {
        "name": "deleted_at",
        "dbType": "datetime:nullable",
        "htmlType": "date",
        "validations": null,
        "searchable": false,
        "fillable": false,
        "primary": false,
        "inForm": false,
        "inIndex": false,
        "inView": false
    },
    {
        "name": "created_at",
        "dbType": "datetime:nullable",
        "htmlType": "date",
        "validations": null,
        "searchable": false,
        "fillable": false,
        "primary": false,
        "inForm": false,
        "inIndex": false,
        "inView": false
    },
    {
        "name": "updated_at",
        "dbType": "datetime:nullable",
        "htmlType": "date",
        "validations": null,
        "searchable": false,
        "fillable": false,
        "primary": false,
        "inForm": false,
        "inIndex": false,
        "inView": false
    }
]